[
    {
        "ID": "PXL_20220918_115850628.MP",
        "filenames": {
            "filename": [
                "/photos/2022/PXL_20220918_115850628.MP-medium.jpeg",
                "/photos/2022/PXL_20220918_115850628.MP-small.webp",
                "/photos/2022/PXL_20220918_115850628.MP-small.jpeg",
                "/photos/2022/PXL_20220918_115850628.MP-medium.webp",
                "/photos/2022/PXL_20220918_115850628.MP-large.jpeg",
                "/photos/2022/PXL_20220918_115850628.MP-large.webp"
            ]
        },
        "exif": {
            "Camera": "Google Pixel 6a",
            "DateTime": "2022-09-18T17:43:50+05:45",
            "GPSLocation": {
                "Latitude": "27.7049444444444",
                "Longitude": "85.30725"
            }
        },
        "location": "Kathmandu, Nepal",
        "description": "I took this image at Shree Kaal Bhairav Temple while visiting Durbar Square in Kathmandu."
    },
    {
        "ID": "PXL_20220918_104155771",
        "filenames": {
            "filename": [
                "/photos/2022/PXL_20220918_104155771-medium.jpeg",
                "/photos/2022/PXL_20220918_104155771-small.webp",
                "/photos/2022/PXL_20220918_104155771-small.jpeg",
                "/photos/2022/PXL_20220918_104155771-medium.webp",
                "/photos/2022/PXL_20220918_104155771-large.jpeg",
                "/photos/2022/PXL_20220918_104155771-large.webp"
            ]
        },
        "exif": {
            "Camera": "Google Pixel 6a",
            "DateTime": "2022-09-18T16:26:55+05:45",
            "GPSLocation": {
                "Latitude": "27.7153055555556",
                "Longitude": "85.2902194444444"
            }
        },
        "location": "Kathmandu, Nepal",
        "description": "I took this at Swayambhu Mahachaitya (also called the \"Monkey Temple\") in Kathmandu. Believed to date back to 460 A.D., it was built by King Manadeva, and by the 13th century, it had become an important center of Buddhism."
    },
    {
        "ID": "PXL_20220917_061253214",
        "filenames": {
            "filename": [
                "/photos/2022/PXL_20220917_061253214-medium.jpeg",
                "/photos/2022/PXL_20220917_061253214-small.webp",
                "/photos/2022/PXL_20220917_061253214-medium.webp",
                "/photos/2022/PXL_20220917_061253214-small.jpeg",
                "/photos/2022/PXL_20220917_061253214-large.jpeg",
                "/photos/2022/PXL_20220917_061253214-large.webp"
            ]
        },
        "exif": {
            "Camera": "Google Pixel 6a",
            "DateTime": "2022-09-17T11:57:53+05:45",
            "GPSLocation": {
                "Latitude": "27.7112277777778",
                "Longitude": "85.3465"
            }
        },
        "location": "Kathmandu, Nepal",
        "description": "I took this at the Pashupatinath Temple in 2022. The temple is located on both banks of the Bagmati River on Kathmandu's eastern outskirts."
    },
    {
        "ID": "PXL_20220923_094145536",
        "filenames": {
            "filename": [
                "/photos/2022/PXL_20220923_094145536-medium.jpeg",
                "/photos/2022/PXL_20220923_094145536-small.webp",
                "/photos/2022/PXL_20220923_094145536-small.jpeg",
                "/photos/2022/PXL_20220923_094145536-medium.webp",
                "/photos/2022/PXL_20220923_094145536-large.jpeg",
                "/photos/2022/PXL_20220923_094145536-large.webp"
            ]
        },
        "exif": {
            "Camera": "Google Pixel 6a",
            "DateTime": "2022-09-23T15:11:45+05:30",
            "GPSLocation": {
                "Latitude": "28.593",
                "Longitude": "77.2460944444444"
            }
        },
        "location": "New Delhi, Delhi, India",
        "description": "I captured this image at the tomb of the noble Isa Khan Niazi, located within the Humayun's Tomb complex in Delhi, India. I visited here in 2022."
    },
    {
        "ID": "PXL_20220329_122940042",
        "filenames": {
            "filename": [
                "/photos/2022/PXL_20220329_122940042-medium.jpeg",
                "/photos/2022/PXL_20220329_122940042-small.webp",
                "/photos/2022/PXL_20220329_122940042-small.jpeg",
                "/photos/2022/PXL_20220329_122940042-medium.webp",
                "/photos/2022/PXL_20220329_122940042-large.jpeg",
                "/photos/2022/PXL_20220329_122940042-large.webp"
            ]
        },
        "exif": {
            "Camera": "Google Pixel 4a (5G)",
            "DateTime": "2022-03-29T14:29:40+02:00",
            "GPSLocation": {
                "Latitude": "45.4343638888889",
                "Longitude": "12.339375"
            }
        },
        "location": "Venice, Italy",
        "description": "I took this at Saint Mark's Basilica (Basilica di San Marco) in Venice. Originally, this building was intended as an extension of the Doge’s Palace; however, the construction of the Basilica of St. Mark, which began in 828 and concluded in 832, was undertaken to house the body of St. Mark the Apostle, who was brought from Alexandria and named protector of the city."
    },
    {
        "ID": "PXL_20220918_012328620",
        "filenames": {
            "filename": [
                "/photos/2022/PXL_20220918_012328620-medium.jpeg",
                "/photos/2022/PXL_20220918_012328620-small.webp",
                "/photos/2022/PXL_20220918_012328620-medium.webp",
                "/photos/2022/PXL_20220918_012328620-small.jpeg",
                "/photos/2022/PXL_20220918_012328620-large.jpeg",
                "/photos/2022/PXL_20220918_012328620-large.webp"
            ]
        },
        "exif": {
            "Camera": "Google Pixel 6a",
            "DateTime": "2022-09-18T07:08:28+05:45",
            "GPSLocation": {
                "Latitude": "27.5485194444444",
                "Longitude": "86.6072055555556"
            }
        },
        "location": "Nepal",
        "description": "When I was in Kathmandu, I had the choice to either fly in a fixed-wing aircraft around Everest or take a helicopter to Everest Base Camp. I chose the flight around Everest because it was significantly cheaper and felt safer. I took this picture from the window."
    },
    {
        "ID": "PXL_20220915_120733752",
        "filenames": {
            "filename": [
                "/photos/2022/PXL_20220915_120733752-medium.jpeg",
                "/photos/2022/PXL_20220915_120733752-small.webp",
                "/photos/2022/PXL_20220915_120733752-small.jpeg",
                "/photos/2022/PXL_20220915_120733752-medium.webp",
                "/photos/2022/PXL_20220915_120733752-large.jpeg",
                "/photos/2022/PXL_20220915_120733752-large.webp"
            ]
        },
        "exif": {
            "Camera": "Google Pixel 6a",
            "DateTime": "2022-09-15T17:37:33+05:30",
            "GPSLocation": {
                "Latitude": "28.6496972222222",
                "Longitude": "77.1900388888889"
            }
        },
        "location": "Delhi, India",
        "description": "A quick visit to the market in Delhi"
    }
]
